blec/__init__.py
blec/__main__.py
blec/__version__.py
blec/_main.py
blec/tests/__init__.py
blec/tests/test_blec.py
blec-1.2.0.dist-info/LICENSE
blec-1.2.0.dist-info/METADATA
blec-1.2.0.dist-info/WHEEL
blec-1.2.0.dist-info/entry_points.txt
blec-1.2.0.dist-info/top_level.txt
blec-1.2.0.dist-info/RECORD
