Metadata-Version: 2.1
Name: blec
Version: 1.2.0
Summary: Alpha blending calculator
Home-page: https://github.com/igrmk/blec
Author: igrmk
Author-email: igrmkx@gmail.com
License: UNKNOWN
Platform: UNKNOWN
Classifier: Programming Language :: Python :: 3
Classifier: License :: OSI Approved :: MIT License
Classifier: Operating System :: OS Independent
Requires-Python: >=3.0
Requires-Dist: importlib-metadata ; python_version < "3.8"
